odoo/addons/account_fiscal_year_closing/README.rst
odoo/addons/account_fiscal_year_closing/__init__.py
odoo/addons/account_fiscal_year_closing/__manifest__.py
odoo/addons/account_fiscal_year_closing/i18n/account_fiscal_year_closing.pot
odoo/addons/account_fiscal_year_closing/i18n/es.po
odoo/addons/account_fiscal_year_closing/i18n/fr.po
odoo/addons/account_fiscal_year_closing/i18n/hr.po
odoo/addons/account_fiscal_year_closing/i18n/it.po
odoo/addons/account_fiscal_year_closing/i18n/nl_NL.po
odoo/addons/account_fiscal_year_closing/i18n/pt.po
odoo/addons/account_fiscal_year_closing/i18n/pt_BR.po
odoo/addons/account_fiscal_year_closing/migrations/12.0.1.2.0/pre-migration.py
odoo/addons/account_fiscal_year_closing/models/__init__.py
odoo/addons/account_fiscal_year_closing/models/account_fiscalyear_closing.py
odoo/addons/account_fiscal_year_closing/models/account_fiscalyear_closing_abstract.py
odoo/addons/account_fiscal_year_closing/models/account_fiscalyear_closing_template.py
odoo/addons/account_fiscal_year_closing/models/account_move.py
odoo/addons/account_fiscal_year_closing/readme/CONFIGURE.rst
odoo/addons/account_fiscal_year_closing/readme/CONTRIBUTORS.rst
odoo/addons/account_fiscal_year_closing/readme/DESCRIPTION.rst
odoo/addons/account_fiscal_year_closing/readme/USAGE.rst
odoo/addons/account_fiscal_year_closing/security/account_fiscalyear_closing_security.xml
odoo/addons/account_fiscal_year_closing/security/ir.model.access.csv
odoo/addons/account_fiscal_year_closing/static/description/icon.png
odoo/addons/account_fiscal_year_closing/static/description/icon.svg
odoo/addons/account_fiscal_year_closing/static/description/index.html
odoo/addons/account_fiscal_year_closing/tests/__init__.py
odoo/addons/account_fiscal_year_closing/tests/test_account_fiscal_year_closing.py
odoo/addons/account_fiscal_year_closing/views/account_fiscalyear_closing_template_views.xml
odoo/addons/account_fiscal_year_closing/views/account_fiscalyear_closing_views.xml
odoo12_addon_account_fiscal_year_closing-12.0.1.2.0.dist-info/METADATA
odoo12_addon_account_fiscal_year_closing-12.0.1.2.0.dist-info/WHEEL
odoo12_addon_account_fiscal_year_closing-12.0.1.2.0.dist-info/top_level.txt
odoo12_addon_account_fiscal_year_closing-12.0.1.2.0.dist-info/RECORD
